{

   "appName":"Video player",
   
   "adCounter":3,
   
   "startApp":"207329894",
   
   "adAppId":"ca-app-pub-3940256099942544~3347511713",
   
   "adBannerAd":"ca-app-pub-4276485780311635/1737101460",
   "adNativeAd":"ca-app-pub-4276485780311635/1006473728",
   "adInterstitialAd":"",
   
   "fbBannerAd":"1137537866614182_1137538493280786",
   "fbNativeAd":"",
   "fbInterstitialAd":"",
   
   "packageName":"com.veddomaan.downloaderfere",
   
   "storeName":"com.veddomaan.downloaderfere"
   
}
